natrixclient/__init__.py
natrixclient/__version__.py
natrixclient/api.py
natrixclient/console.py
natrixclient/rabbitmq.py
natrixclient/command/__init__.py
natrixclient/command/ncheck.py
natrixclient/command/ndns.py
natrixclient/command/ndnserror.py
natrixclient/command/nhttp.py
natrixclient/command/nperformance.py
natrixclient/command/nping.py
natrixclient/command/nreport.py
natrixclient/command/ntraceroute.py
natrixclient/command/storage.py
natrixclient/command/check/__init__.py
natrixclient/command/check/hardware.py
natrixclient/command/check/iplocation.py
natrixclient/command/check/ippublic.py
natrixclient/command/check/ipregion.py
natrixclient/command/check/network.py
natrixclient/command/check/speed.py
natrixclient/command/check/system.py
natrixclient/command/http/__init__.py
natrixclient/command/http/httperror.py
natrixclient/command/performance/__init__.py
natrixclient/command/ping/__init__.py
natrixclient/command/ping/pyping.py
natrixclient/common/__init__.py
natrixclient/common/config.py
natrixclient/common/const.py
natrixclient/common/nettools.py
natrixclient/common/utils.py
natrixclient/conf/etc/natrix/natrix.ini
natrixclient/conf/etc/natrix/natrixclient.daemon
natrixclient/conf/etc/systemd/system/natrixclient.service
natrixclient/data/ip2region.db
natrixclient-0.1.3.data/scripts/natrix
natrixclient-0.1.3.dist-info/LICENSE
natrixclient-0.1.3.dist-info/METADATA
natrixclient-0.1.3.dist-info/WHEEL
natrixclient-0.1.3.dist-info/top_level.txt
natrixclient-0.1.3.dist-info/RECORD
