Metadata-Version: 2.1
Name: natrixclient
Version: 0.1.3
Summary: Client For Natrix - An Open Source Cloud Automation Testing Project
Home-page: https://github.com/creditease-natrix/natrixclient
Author: JamesZOU
Author-email: zouzhicheng@foxmail.com
Maintainer: JamesZOU
Maintainer-email: zouzhicheng@foxmail.com
License: UNKNOWN
Download-URL: https://github.com/creditease-natrix/natrixclient
Platform: RedHat
Platform: Ubuntu
Platform: Raspbian
Classifier: Development Status :: 3 - Alpha
Classifier: Intended Audience :: Developers
Classifier: Intended Audience :: End Users/Desktop
Classifier: Intended Audience :: Information Technology
Classifier: Intended Audience :: System Administrators
Classifier: License :: OSI Approved :: Apache Software License
Classifier: Operating System :: POSIX :: Linux
Classifier: Programming Language :: Python :: 2
Classifier: Programming Language :: Python :: 2.7
Classifier: Programming Language :: Python :: 3
Classifier: Programming Language :: Python :: 3.4
Classifier: Programming Language :: Python :: 3.5
Classifier: Programming Language :: Python :: 3.6
Classifier: Programming Language :: Python :: 3.7
Classifier: Programming Language :: Python :: 3.8
Classifier: Topic :: Software Development :: Libraries :: Python Modules
Classifier: Topic :: System :: Networking
Classifier: Topic :: Utilities
Requires-Python: >=2.7,!=3.0.*,!=3.1.*
Requires-Dist: requests (>=2.18.4)
Requires-Dist: selenium (>=3.14.0)
Requires-Dist: pika (>=0.12.0)
Requires-Dist: python-hosts (>=0.4.5)
Requires-Dist: apscheduler (>=3.5.3)
Requires-Dist: dnspython (>=1.15.0)
Requires-Dist: psutil (>=5.4.8)
Requires-Dist: netifaces (>=0.10.7)
Requires-Dist: distro (>=1.3.0)
Requires-Dist: pycurl (>=7.43.0.2)
Requires-Dist: python-crontab (>=2.3.6)
Requires-Dist: enum34 (>=1.1.6)
